easy_sqlite
