Metadata-Version: 1.1
Name: easy-sqlite
Version: 1.0.11
Summary: This Library makes using the sqlite3 library much easier and faster.
Home-page: https://github.com/CalderWhite/easy_sqlite
Author: Calder White
Author-email: calderwhite1@gmail.com
License: UNKNOWN
Download-URL: https://github.com/CalderWhite/easy_sqlite/archive/master.zip
Platform: UNKNOWN
